setup.py
electronfactors/__init__.py
electronfactors.egg-info/PKG-INFO
electronfactors.egg-info/SOURCES.txt
electronfactors.egg-info/dependency_links.txt
electronfactors.egg-info/top_level.txt
electronfactors/ellipse/__init__.py
electronfactors/ellipse/equivalent.py
electronfactors/ellipse/utilities.py
electronfactors/inputs/__init__.py
electronfactors/inputs/convert_merge.py
electronfactors/inputs/genericshape.py
electronfactors/inputs/rawcoords.py
electronfactors/measurement/__init__.py
electronfactors/measurement/utilities.py
electronfactors/model/__init__.py
electronfactors/model/parameterise.py
electronfactors/model/sort.py
electronfactors/model/threshold.py
electronfactors/model/utilities.py
electronfactors/reports/__init__.py
electronfactors/reports/html.py
electronfactors/reports/interactive.py
electronfactors/reports/utilities.py
electronfactors/visuals/__init__.py
electronfactors/visuals/histogram.py
electronfactors/visuals/print_generic.py
electronfactors/visuals/print_to_scale.py
electronfactors/visuals/shape_display.py
electronfactors/visuals/utilities.py
test/test_equivalentellipse.py
test/test_inputs.py
test/test_poi.py
test/test_run_demo_notebooks.py
test/test_run_paper_notebooks.py
test/test_run_standalone_notebooks.py