Metadata-Version: 1.0
Name: electronfactors
Version: 0.1.5
Summary: Predict electron insert factors
Home-page: https://github.com/SimonBiggs/electronfactors
Author: Simon Biggs
Author-email: mail@simonbiggs.net
License: AGPL3+
Platform: UNKNOWN
